xj_payment/__init__.py
xj_payment/admin.py
xj_payment/apps.py
xj_payment/common.py
xj_payment/models.py
xj_payment/urls.py
xj_payment/apis/__init__.py
xj_payment/apis/alipay.py
xj_payment/apis/payment.py
xj_payment/apis/payment_alipay.py
xj_payment/apis/payment_apis.py
xj_payment/apis/payment_status.py
xj_payment/apis/payment_status_apis.py
xj_payment/apis/payment_unionpay.py
xj_payment/apis/payment_wechat.py
xj_payment/apis/transaction_inquiry.py
xj_payment/services/__init__.py
xj_payment/services/payment_alipay_service.py
xj_payment/services/payment_logical_process_service.py
xj_payment/services/payment_satus_service.py
xj_payment/services/payment_service.py
xj_payment/services/payment_unionpay_service.py
xj_payment/services/payment_wechat_service.py
xj_payment/utils/__init__.py
xj_payment/utils/alipay_utils.py
xj_payment/utils/base.py
xj_payment/utils/common.py
xj_payment/utils/custom_response.py
xj_payment/utils/custom_tool.py
xj_payment/utils/j_config.py
xj_payment/utils/j_dict.py
xj_payment/utils/join_list.py
xj_payment/utils/json_util.py
xj_payment/utils/model_handle.py
xj_payment/utils/unionpay_utils.py
xj_payment/utils/user_wrapper.py
xj_payment/utils/utility_method.py
xj_payment/utils/utils.py
xj_payment/utils/utils_v1.py
xj_payment/utils/wechat_utils.py
xj_payment-1.0.84.dist-info/METADATA
xj_payment-1.0.84.dist-info/WHEEL
xj_payment-1.0.84.dist-info/top_level.txt
xj_payment-1.0.84.dist-info/RECORD
