Metadata-Version: 2.1
Name: xj-payment
Version: 1.0.84
Summary: 支付模块
License: apache 3.0
Requires-Dist: python-alipay-sdk >=3.1.0
Requires-Dist: wechatpy >=1.8.18
Requires-Dist: pyOpenSSL >=22.0.0
Requires-Dist: rsa >=4.9
Requires-Dist: crypto >=1.4.1
Requires-Dist: wechatpayv3
Requires-Dist: celery
Requires-Dist: xmltodict
